biox/__init__.py
biox/__main__.py
biox/core/base.py
biox/core/binary.py
biox/core/command.py
biox/core/conf.py
biox/core/dataset.py
biox/core/execute.py
biox/core/job.py
biox/core/log.py
biox/core/status.py
biox/core/util.py
biox/core/workflow.py
biox/dsl/codegen.py
biox/dsl/parser.py
biox/dsl/token.py
xbio-0.1.0.dist-info/METADATA
xbio-0.1.0.dist-info/WHEEL
xbio-0.1.0.dist-info/top_level.txt
xbio-0.1.0.dist-info/RECORD
