Metadata-Version: 2.1
Name: xbio
Version: 0.1.0
Summary: A bioinformatics workflow management tool.
Author-email: dwpeng <dwpeng1122@foxmail.com>
License: MIT
Requires-Python: >=3.11
Requires-Dist: pyparsing >=3.1.2
Requires-Dist: ujson >=5.10.0
Requires-Dist: SQLAlchemy >=2.0.31
Requires-Dist: rich >=13.7.1
Provides-Extra: fastapi
Requires-Dist: fastapi >=0.111.0 ; extra == 'fastapi'
